[
    {
        "id": "7x-Df6Uz7_UJ",
        "title": "Epiregulon: Single-cell transcription factor activity inference to predict drug response and drivers of cell states",
        "link": "https://www.nature.com/articles/s41467-025-62252-5.pdf",
        "filename": "7x-Df6Uz7_UJ_epiregulon-single-cell-transcription-factor-activity-inference-to-predict-drug-response-and-drivers-of-cell-states.pdf"
    },
    {
        "id": "GNboKgrVo3MJ",
        "title": "DETECTION OF NON-TRANSCRIPTIONALLY MEDIATED CHANGES IN TRANSCRIPTION FACTOR ACTIVITY USING MULTIOMIC SINGLE-CELL DATA",
        "link": "https://jscholarship.library.jhu.edu/bitstream/handle/1774.2/68031/CHU-THESIS-2022.pdf?sequence=1",
        "filename": "GNboKgrVo3MJ_detection-of-non-transcriptionally-mediated-changes-in-transcription-factor-activity-using-multiomic-single-cell-data.pdf"
    },
    {
        "id": "x5T-K9hXiEgJ",
        "title": "Mechano-osmotic signals control chromatin state and fate transitions in pluripotent stem cells",
        "link": "https://www.nature.com/articles/s41556-025-01767-x.pdf",
        "filename": "x5T-K9hXiEgJ_mechano-osmotic-signals-control-chromatin-state-and-fate-transitions-in-pluripotent-stem-cells.pdf"
    }
]